ren/__init__.py
pyRen-0.0.0.dist-info/LICENSE
pyRen-0.0.0.dist-info/METADATA
pyRen-0.0.0.dist-info/WHEEL
pyRen-0.0.0.dist-info/top_level.txt
pyRen-0.0.0.dist-info/RECORD
